gpkgstatus/__init__.py
gpkgstatus/entrypoint.py
gpkgstatus/gpkgstatus.py
gpkgstatus/utils/__init__.py
gpkgstatus/utils/config.py
gpkgstatus/utils/json_file_reader.py
gpkgstatus/utils/url_reader.py
gpkgstatus-2.1.3.dist-info/LICENSE
gpkgstatus-2.1.3.dist-info/METADATA
gpkgstatus-2.1.3.dist-info/WHEEL
gpkgstatus-2.1.3.dist-info/entry_points.txt
gpkgstatus-2.1.3.dist-info/top_level.txt
gpkgstatus-2.1.3.dist-info/RECORD
