Metadata-Version: 2.1
Name: gpkgstatus
Version: 2.1.3
Summary: Get Current Package Status from Fedora Updates System
Author: Dhanush Kovi
License: GPL-2.0-or-later
Project-URL: Homepage, https://dkvc.github.io/gpkgstatus/
Project-URL: Documentation, https://dkvc.github.io/gpkgstatus/
Project-URL: Repository, https://github.com/dkvc/gpkgstatus
Keywords: fedora,updates,package,status,fedora-updates,gpkgstatus,bodhi
Classifier: Development Status :: 5 - Production/Stable
Classifier: Environment :: Console
Classifier: Topic :: Utilities
Classifier: Intended Audience :: Developers
Classifier: License :: OSI Approved :: GNU General Public License v2 (GPLv2)
Classifier: Operating System :: OS Independent
Classifier: Programming Language :: Python :: 3.8
Classifier: Programming Language :: Python :: 3.9
Classifier: Programming Language :: Python :: 3.10
Classifier: Programming Language :: Python :: 3.11
Requires-Python: >=3.8
License-File: LICENSE
Requires-Dist: requests (==2.31.0)
Requires-Dist: termcolor (==2.2.0)
Provides-Extra: dev
Requires-Dist: altgraph (>=0.17.3) ; extra == 'dev'
Requires-Dist: astroid (>=2.14.2) ; extra == 'dev'
Requires-Dist: attrs (>=22.2.0) ; extra == 'dev'
Requires-Dist: black (>=23.1.0) ; extra == 'dev'
Requires-Dist: bpyutils (>=0.5.8) ; extra == 'dev'
Requires-Dist: certifi (>=2022.12.7) ; extra == 'dev'
Requires-Dist: charset-normalizer (>=3.0.1) ; extra == 'dev'
Requires-Dist: click (>=8.1.3) ; extra == 'dev'
Requires-Dist: dill (>=0.3.6) ; extra == 'dev'
Requires-Dist: docopt (>=0.6.2) ; extra == 'dev'
Requires-Dist: fastjsonschema (>=2.16.2) ; extra == 'dev'
Requires-Dist: idna (>=3.4) ; extra == 'dev'
Requires-Dist: iniconfig (>=2.0.0) ; extra == 'dev'
Requires-Dist: isort (>=5.12.0) ; extra == 'dev'
Requires-Dist: Jinja2 (>=3.1.2) ; extra == 'dev'
Requires-Dist: lazy-object-proxy (>=1.9.0) ; extra == 'dev'
Requires-Dist: MarkupSafe (>=2.1.2) ; extra == 'dev'
Requires-Dist: mccabe (>=0.7.0) ; extra == 'dev'
Requires-Dist: mypy-extensions (>=1.0.0) ; extra == 'dev'
Requires-Dist: packaging (>=23.0) ; extra == 'dev'
Requires-Dist: pathspec (>=0.11.0) ; extra == 'dev'
Requires-Dist: pdoc (>=12.3.1) ; extra == 'dev'
Requires-Dist: pipreqs (>=0.4.11) ; extra == 'dev'
Requires-Dist: pipupgrade (>=1.12.0) ; extra == 'dev'
Requires-Dist: platformdirs (>=3.0.0) ; extra == 'dev'
Requires-Dist: pluggy (>=1.0.0) ; extra == 'dev'
Requires-Dist: Pygments (>=2.14.0) ; extra == 'dev'
Requires-Dist: pyinstaller (>=5.7.0) ; extra == 'dev'
Requires-Dist: pyinstaller-hooks-contrib (>=2022.15) ; extra == 'dev'
Requires-Dist: pylint (>=2.16.2) ; extra == 'dev'
Requires-Dist: pytest (>=7.2.1) ; extra == 'dev'
Requires-Dist: requests (>=2.28.2) ; extra == 'dev'
Requires-Dist: termcolor (>=2.2.0) ; extra == 'dev'
Requires-Dist: tomlkit (>=0.11.6) ; extra == 'dev'
Requires-Dist: urllib3 (>=1.26.14) ; extra == 'dev'
Requires-Dist: validate-pyproject (>=0.12.1) ; extra == 'dev'
Requires-Dist: wrapt (>=1.14.1) ; extra == 'dev'
Requires-Dist: yarg (>=0.1.9) ; extra == 'dev'
